joulectl/__init__.py
joulectl/commands/__init__.py
joulectl/commands/deploycmds.py
joulectl/commands/inspectcmds.py
joulectl/commands/listcmds.py
joulectl/commands/ucmgmtcmds.py
joulectl/commands/undeploycmds.py
joulectl/config/__init__.py
joulectl/config/config.py
joulectl/config/file.py
joulectl/joule.py
joulectl/joulecomms.py
joulectl-0.1.5.dist-info/AUTHORS
joulectl-0.1.5.dist-info/LICENSE
joulectl-0.1.5.dist-info/METADATA
joulectl-0.1.5.dist-info/WHEEL
joulectl-0.1.5.dist-info/entry_points.txt
joulectl-0.1.5.dist-info/RECORD
