Metadata-Version: 2.3
Name: joulectl
Version: 0.1.5
Summary: Joule CLI tool to manage Joule transports, streams and use cases
License: MIT
Keywords: joule,streaming
Author: Lyndon Adams
Author-email: lyndon.adams@fractalworks.io
Requires-Python: >=3.10
Classifier: License :: OSI Approved :: MIT License
Requires-Dist: click (>=8.1.8,<9.0.0)
Requires-Dist: pyyaml (>=6.0,<7.0)
Requires-Dist: requests (>=2.32.3,<3.0.0)
Requires-Dist: tabulate (>=0.9.0,<1.0.0)
Project-URL: Documentation, https://docs.fractalworks.io/joule
Project-URL: Homepage, https://https://getjoule.io/
